schedrem/__init__.py
schedrem/__main__.py
schedrem/config.py
schedrem/manager.py
schedrem/util.py
schedrem/assets/alert.wav
schedrem/assets/schedrem.ico
schedrem-1.5.2.dist-info/METADATA
schedrem-1.5.2.dist-info/WHEEL
schedrem-1.5.2.dist-info/entry_points.txt
schedrem-1.5.2.dist-info/licenses/LICENSE
schedrem-1.5.2.dist-info/RECORD
