Metadata-Version: 2.4
Name: schedrem
Version: 1.5.2
Summary: A cross-platform task scheduler and reminder configured in YAML.
Project-URL: Homepage, https://github.com/hikyae/schedrem
Project-URL: Issues, https://github.com/hikyae/schedrem/issues
Author-email: hikyae <h1ky43@gmail.com>
License-File: LICENSE
Keywords: YAML,cross-platform,desktop,reminder,scheduler,task,tkinter
Classifier: Framework :: AsyncIO
Classifier: Framework :: Pydantic :: 2
Classifier: License :: OSI Approved :: MIT License
Classifier: Operating System :: OS Independent
Classifier: Programming Language :: Python :: 3
Requires-Python: >=3.11
Requires-Dist: psutil>=6.1.0
Requires-Dist: pyaudio>=0.2.14
Requires-Dist: pydantic>=2.9.1
Requires-Dist: pyyaml>=6.0.2
Requires-Dist: watchdog>=5.0.2
Provides-Extra: dev
Requires-Dist: freezegun; extra == 'dev'
Requires-Dist: pytest; extra == 'dev'
Requires-Dist: ruff; extra == 'dev'
